khwarizmi/__init__.py
khwarizmi/equations.py
khwarizmi/exc.py
khwarizmi/expression.py
khwarizmi/linear.py
khwarizmi/misc.py
khwarizmi/polynomials.py
khwarizmi/quadratic.py
khwarizmi/terms_ops.py
khwarizmi-0.5.dist-info/LICENSE
khwarizmi-0.5.dist-info/METADATA
khwarizmi-0.5.dist-info/WHEEL
khwarizmi-0.5.dist-info/top_level.txt
khwarizmi-0.5.dist-info/RECORD
