Metadata-Version: 2.1
Name: khwarizmi
Version: 0.5
Summary: Because algebra is pretty
Home-page: https://github.com/lpereyrasantiago/khwarizmi
Author: lpereyrasantiago
Author-email: santiagolopezpereyra@gmail.com
License: GNU GENERAL PUBLIC LICENSE
Platform: UNKNOWN
